process_logging/__init__.py
process_logging/logger.py
process_logging-0.2.0.dist-info/METADATA
process_logging-0.2.0.dist-info/WHEEL
process_logging-0.2.0.dist-info/top_level.txt
process_logging-0.2.0.dist-info/RECORD
