Metadata-Version: 2.1
Name: process-logging
Version: 0.2.0
Summary: Simple logging module run on process with python logging
Author: kyon333
Author-email: originky2@gmail.com
Keywords: logging,multiprocess
Classifier: Programming Language :: Python :: 3.10
Requires-Python: >=3.10
Requires-Dist: setproctitle
